setup.py
surfGuide/__init__.py
surfGuide/entry.py
surfGuide.egg-info/PKG-INFO
surfGuide.egg-info/SOURCES.txt
surfGuide.egg-info/dependency_links.txt
surfGuide.egg-info/entry_points.txt
surfGuide.egg-info/requires.txt
surfGuide.egg-info/top_level.txt
surfGuide.egg-info/zip-safe
surfGuide/menus/__init__.py
surfGuide/menus/argsGuide.py
surfGuide/menus/conBase.py
surfGuide/menus/createSurf.py
surfGuide/menus/editEvent.py
surfGuide/menus/editExpression.py
surfGuide/menus/editFilter.py
surfGuide/menus/editJprobe.py
surfGuide/menus/fileBrowser.py
surfGuide/menus/fileChecker.py
surfGuide/menus/lbcClient.py
surfGuide/menus/packProduct.py
surfGuide/menus/pubLoader.py
surfGuide/menus/publish.py
surfGuide/menus/saveasWidget.py
surfGuide/menus/showVersions.py
surfGuide/menus/structSelector.py
surfGuide/menus/surfExpression.py
surfGuide/menus/surfGuide.py
surfGuide/menus/surfThread.py
surfGuide/menus/typeChooser.py