Metadata-Version: 1.1
Name: surfGuide
Version: 0.4.5
Summary: surfGuide is a tool that guide you to use surftrace.
Home-page: https://github.com/aliyun/surftrace
Author: liaozhaoyan
Author-email: zhoayan.liao@linux.alibaba.com
License: LGPL
Keywords: linux kernel trace
Platform: UNKNOWN
Classifier: Topic :: System :: Operating System Kernels :: Linux
Classifier: Programming Language :: Python
Classifier: Programming Language :: Python :: 2
Classifier: Programming Language :: Python :: 2.7
Classifier: Programming Language :: Python :: 3
Classifier: Programming Language :: Python :: 3.5
Classifier: Programming Language :: Python :: 3.6
Classifier: Programming Language :: Python :: 3.7
Classifier: Programming Language :: Python :: 3.8
Classifier: Programming Language :: Python :: 3.9
Classifier: Programming Language :: Python :: Implementation :: PyPy
